{
  "source": "official_json_api",
  "source_url": "https://api-statistic.reg.cmu.ac.th/v1/data/s002001?year=2569&semester=1&semestercurrent=1&admityear=67&fac=999&level=999&sex=999&student_type=999&nat=999",
  "endpoint": "data/s002001",
  "params": {
    "year": "2569",
    "semester": "1",
    "semestercurrent": "1",
    "admityear": "67",
    "fac": "999",
    "level": "999",
    "sex": "999",
    "student_type": "999",
    "nat": "999"
  },
  "fetched_at_utc": "2026-07-09T08:53:37+00:00",
  "payload": {
    "header": [
      {
        "row": "1",
        "iterate": 1,
        "field": [
          {
            "name": "คณะ",
            "rowspan": "2",
            "colspan": "1"
          },
          {
            "name": "ออกรหัส",
            "rowspan": "1",
            "colspan": "3"
          },
          {
            "name": "สละสิทธิ์",
            "rowspan": "1",
            "colspan": "3"
          },
          {
            "name": "คงเหลือ",
            "rowspan": "1",
            "colspan": "3"
          }
        ]
      },
      {
        "row": "2",
        "iterate": 3,
        "field": [
          {
            "name": "ชาย",
            "rowspan": "1",
            "colspan": "1"
          },
          {
            "name": "หญิง",
            "rowspan": "1",
            "colspan": "1"
          },
          {
            "name": "รวม",
            "rowspan": "1",
            "colspan": "1"
          }
        ]
      }
    ],
    "data": [
      {
        "faculty": "คณะมนุษยศาสตร์",
        "c1": 309,
        "c2": 693,
        "c3": 1002,
        "c4": 15,
        "c5": 28,
        "c6": 43,
        "c7": 294,
        "c8": 665,
        "c9": 959
      },
      {
        "faculty": "คณะศึกษาศาสตร์",
        "c1": 225,
        "c2": 368,
        "c3": 593,
        "c4": 15,
        "c5": 16,
        "c6": 31,
        "c7": 210,
        "c8": 352,
        "c9": 562
      },
      {
        "faculty": "คณะวิจิตรศิลป์",
        "c1": 157,
        "c2": 309,
        "c3": 466,
        "c4": 7,
        "c5": 9,
        "c6": 16,
        "c7": 150,
        "c8": 300,
        "c9": 450
      },
      {
        "faculty": "คณะสังคมศาสตร์",
        "c1": 113,
        "c2": 283,
        "c3": 396,
        "c4": 16,
        "c5": 32,
        "c6": 48,
        "c7": 97,
        "c8": 251,
        "c9": 348
      },
      {
        "faculty": "คณะวิทยาศาสตร์",
        "c1": 383,
        "c2": 593,
        "c3": 976,
        "c4": 28,
        "c5": 34,
        "c6": 62,
        "c7": 355,
        "c8": 559,
        "c9": 914
      },
      {
        "faculty": "คณะวิศวกรรมศาสตร์",
        "c1": 976,
        "c2": 509,
        "c3": 1485,
        "c4": 46,
        "c5": 32,
        "c6": 78,
        "c7": 930,
        "c8": 477,
        "c9": 1407
      },
      {
        "faculty": "คณะแพทยศาสตร์",
        "c1": 182,
        "c2": 166,
        "c3": 348,
        "c4": 5,
        "c5": 10,
        "c6": 15,
        "c7": 177,
        "c8": 156,
        "c9": 333
      },
      {
        "faculty": "คณะเกษตรศาสตร์",
        "c1": 197,
        "c2": 390,
        "c3": 587,
        "c4": 11,
        "c5": 13,
        "c6": 24,
        "c7": 186,
        "c8": 377,
        "c9": 563
      },
      {
        "faculty": "คณะทันตแพทยศาสตร์",
        "c1": 64,
        "c2": 177,
        "c3": 241,
        "c4": 4,
        "c5": 7,
        "c6": 11,
        "c7": 60,
        "c8": 170,
        "c9": 230
      },
      {
        "faculty": "คณะเภสัชศาสตร์",
        "c1": 89,
        "c2": 135,
        "c3": 224,
        "c4": 6,
        "c5": 5,
        "c6": 11,
        "c7": 83,
        "c8": 130,
        "c9": 213
      },
      {
        "faculty": "คณะเทคนิคการแพทย์",
        "c1": 114,
        "c2": 256,
        "c3": 370,
        "c4": 6,
        "c5": 7,
        "c6": 13,
        "c7": 108,
        "c8": 249,
        "c9": 357
      },
      {
        "faculty": "คณะพยาบาลศาสตร์",
        "c1": 62,
        "c2": 348,
        "c3": 410,
        "c4": 4,
        "c5": 16,
        "c6": 20,
        "c7": 58,
        "c8": 332,
        "c9": 390
      },
      {
        "faculty": "คณะอุตสาหกรรมเกษตร",
        "c1": 134,
        "c2": 387,
        "c3": 521,
        "c4": 7,
        "c5": 9,
        "c6": 16,
        "c7": 127,
        "c8": 378,
        "c9": 505
      },
      {
        "faculty": "คณะสัตวแพทยศาสตร์",
        "c1": 45,
        "c2": 80,
        "c3": 125,
        "c4": 3,
        "c5": 2,
        "c6": 5,
        "c7": 42,
        "c8": 78,
        "c9": 120
      },
      {
        "faculty": "คณะบริหารธุรกิจ",
        "c1": 226,
        "c2": 574,
        "c3": 800,
        "c4": 14,
        "c5": 21,
        "c6": 35,
        "c7": 212,
        "c8": 553,
        "c9": 765
      },
      {
        "faculty": "คณะเศรษฐศาสตร์",
        "c1": 274,
        "c2": 465,
        "c3": 739,
        "c4": 21,
        "c5": 36,
        "c6": 57,
        "c7": 253,
        "c8": 429,
        "c9": 682
      },
      {
        "faculty": "คณะสถาปัตยกรรมศาสตร์",
        "c1": 88,
        "c2": 145,
        "c3": 233,
        "c4": 10,
        "c5": 9,
        "c6": 19,
        "c7": 78,
        "c8": 136,
        "c9": 214
      },
      {
        "faculty": "คณะการสื่อสารมวลชน",
        "c1": 142,
        "c2": 245,
        "c3": 387,
        "c4": 2,
        "c5": 4,
        "c6": 6,
        "c7": 140,
        "c8": 241,
        "c9": 381
      },
      {
        "faculty": "คณะรัฐศาสตร์และรัฐประศาสนศาสตร์",
        "c1": 141,
        "c2": 188,
        "c3": 329,
        "c4": 6,
        "c5": 2,
        "c6": 8,
        "c7": 135,
        "c8": 186,
        "c9": 321
      },
      {
        "faculty": "คณะนิติศาสตร์",
        "c1": 107,
        "c2": 237,
        "c3": 344,
        "c4": 7,
        "c5": 4,
        "c6": 11,
        "c7": 100,
        "c8": 233,
        "c9": 333
      },
      {
        "faculty": "วิทยาลัยศิลปะ สื่อ และเทคโนโลยี",
        "c1": 259,
        "c2": 202,
        "c3": 461,
        "c4": 19,
        "c5": 33,
        "c6": 52,
        "c7": 240,
        "c8": 169,
        "c9": 409
      },
      {
        "faculty": "คณะสาธารณสุขศาสตร์",
        "c1": 15,
        "c2": 19,
        "c3": 34,
        "c4": 2,
        "c5": 0,
        "c6": 2,
        "c7": 13,
        "c8": 19,
        "c9": 32
      },
      {
        "faculty": "วิทยาลัยการศึกษาและการจัดการทางทะเล",
        "c1": 2,
        "c2": 0,
        "c3": 2,
        "c4": 2,
        "c5": 0,
        "c6": 2,
        "c7": 0,
        "c8": 0,
        "c9": 0
      },
      {
        "faculty": "วิทยาลัยนานาชาตินวัตกรรมดิจิทัล",
        "c1": 77,
        "c2": 82,
        "c3": 159,
        "c4": 3,
        "c5": 12,
        "c6": 15,
        "c7": 74,
        "c8": 70,
        "c9": 144
      },
      {
        "faculty": "สถาบันนโยบายสาธารณะ",
        "c1": 22,
        "c2": 28,
        "c3": 50,
        "c4": 8,
        "c5": 10,
        "c6": 18,
        "c7": 14,
        "c8": 18,
        "c9": 32
      },
      {
        "faculty": "สถาบันวิศวกรรมชีวการแพทย์",
        "c1": 6,
        "c2": 6,
        "c3": 12,
        "c4": 0,
        "c5": 0,
        "c6": 0,
        "c7": 6,
        "c8": 6,
        "c9": 12
      },
      {
        "faculty": "สถาบันวิจัยวิทยาศาสตร์สุขภาพ",
        "c1": 10,
        "c2": 11,
        "c3": 21,
        "c4": 2,
        "c5": 2,
        "c6": 4,
        "c7": 8,
        "c8": 9,
        "c9": 17
      },
      {
        "faculty": "วิทยาลัยพหุวิทยาการและสหวิทยาการ",
        "c1": 30,
        "c2": 60,
        "c3": 90,
        "c4": 7,
        "c5": 15,
        "c6": 22,
        "c7": 23,
        "c8": 45,
        "c9": 68
      }
    ],
    "order": "aaal",
    "error": ""
  }
}